README.md
pyfracgen/__init__.py
pyfracgen/buddhabrot.py
pyfracgen/common.py
pyfracgen/images/__init__.py
pyfracgen/images/images.py
pyfracgen/iterfuncs/funcs.py
pyfracgen/julia.py
pyfracgen/lyapunov.py
pyfracgen/mandelbrot.py
pyfracgen/randomwalk.py
pyfracgen/types.py
pyproject.toml
pyfracgen-0.3.0.dist-info/LICENSE
pyfracgen-0.3.0.dist-info/METADATA
pyfracgen-0.3.0.dist-info/WHEEL
pyfracgen-0.3.0.dist-info/RECORD
