Metadata-Version: 2.1
Name: pyfracgen
Version: 0.3.0
Summary: Python Fractal Generation is a package for generating aesthetic fractal images quickly and (hopefully) easily
Home-page: https://github.com/rytheranderson/pyfracgen
License: MIT
Author: Ryther Anderson
Requires-Python: >=3.10,<4.0
Classifier: License :: OSI Approved :: MIT License
Classifier: Programming Language :: Python :: 3
Classifier: Programming Language :: Python :: 3.10
Classifier: Programming Language :: Python :: 3.11
Classifier: Programming Language :: Python :: 3.12
Requires-Dist: matplotlib (>=3.8.2,<4.0.0)
Requires-Dist: nptyping (>=2.5.0,<3.0.0)
Requires-Dist: numba (>=0.59.0rc1)
Requires-Dist: numpy (>=1.26.2,<2.0.0)
Project-URL: Repository, https://github.com/rytheranderson/pyfracgen
